glyphdeck/__init__.py
glyphdeck/_path_constants.py
glyphdeck/config/__init__.py
glyphdeck/config/_logger_config.yaml
glyphdeck/config/logger_config.py
glyphdeck/config/logger_levels.py
glyphdeck/processors/__init__.py
glyphdeck/processors/cascade.py
glyphdeck/processors/llm_handler.py
glyphdeck/processors/sanitiser.py
glyphdeck/tools/__init__.py
glyphdeck/tools/caching.py
glyphdeck/tools/directory_creators.py
glyphdeck/tools/file_importers.py
glyphdeck/tools/logger_interface.py
glyphdeck/tools/logging_.py
glyphdeck/tools/prepper.py
glyphdeck/tools/strings.py
glyphdeck/tools/time.py
glyphdeck/validation/__init__.py
glyphdeck/validation/data_types.py
glyphdeck/validation/validators.py
glyphdeck-1.1.2.dist-info/LICENSE
glyphdeck-1.1.2.dist-info/METADATA
glyphdeck-1.1.2.dist-info/WHEEL
glyphdeck-1.1.2.dist-info/RECORD
