Metadata-Version: 2.1
Name: glyphdeck
Version: 1.1.2
Summary: The glyphdeck library is a comprehensive toolkit designed to streamline & simplify various aspects of asynchronous LLM data processing workflows over high-volume, dense semantic data - like customer feedback, reviews and comments.
Home-page: https://github.com/Kyle-Ross/glyphdeck
License: Elastic-2.0
Keywords: llm,openai,nlp,semantic,langchain
Author: Kyle Ross
Author-email: 107285758+Kyle-Ross@users.noreply.github.com
Requires-Python: >=3.12.0,<4.0.0
Classifier: License :: Other/Proprietary License
Classifier: Programming Language :: Python :: 3
Classifier: Programming Language :: Python :: 3.12
Requires-Dist: diskcache (>=5.6.3,<6.0.0)
Requires-Dist: instructor (>=1.0.3,<2.0.0)
Requires-Dist: openai (>=1.16.2,<2.0.0)
Requires-Dist: openpyxl (>=3.1.2,<4.0.0)
Requires-Dist: oyaml (>=1.0,<2.0)
Requires-Dist: pandas (>=2.2.1,<3.0.0)
Requires-Dist: pydantic (>=2.6.4,<3.0.0)
Requires-Dist: tenacity (>=8.2.3,<9.0.0)
Project-URL: Documentation, https://glyphdeck.readthedocs.io/en/latest/
Project-URL: Repository, https://github.com/Kyle-Ross/glyphdeck
